fh_nbdev/__init__.py
fh_nbdev/_modidx.py
fh_nbdev/core.py
fh_nbdev-0.0.4.dist-info/licenses/LICENSE
fh_nbdev-0.0.4.dist-info/METADATA
fh_nbdev-0.0.4.dist-info/WHEEL
fh_nbdev-0.0.4.dist-info/entry_points.txt
fh_nbdev-0.0.4.dist-info/top_level.txt
fh_nbdev-0.0.4.dist-info/RECORD
