Metadata-Version: 2.4
Name: fh-nbdev
Version: 0.0.4
Summary: FastHTML docs page for nbdev projects
Home-page: https://github.com/AnswerDotAI/fh-nbdev
Author: Isaac Flath
Author-email: Isaac.flath@gmail.com
License: Apache Software License 2.0
Keywords: nbdev jupyter notebook python
Classifier: Development Status :: 4 - Beta
Classifier: Intended Audience :: Developers
Classifier: Natural Language :: English
Classifier: Programming Language :: Python :: 3.7
Classifier: Programming Language :: Python :: 3.8
Classifier: Programming Language :: Python :: 3.9
Classifier: Programming Language :: Python :: 3.10
Classifier: Programming Language :: Python :: 3.11
Classifier: Programming Language :: Python :: 3.12
Classifier: License :: OSI Approved :: Apache Software License
Requires-Python: >=3.7
License-File: LICENSE
Requires-Dist: fastcore
Requires-Dist: execnb
Requires-Dist: nbdev
Requires-Dist: monsterui
Requires-Dist: python-fasthtml
Requires-Dist: beautifulsoup4
Requires-Dist: mistletoe
Provides-Extra: dev
Dynamic: author
Dynamic: author-email
Dynamic: classifier
Dynamic: description
Dynamic: description-content-type
Dynamic: home-page
Dynamic: keywords
Dynamic: license
Dynamic: license-file
Dynamic: provides-extra
Dynamic: requires-dist
Dynamic: requires-python
Dynamic: summary
